ahfhalotools/__init__.py
ahfhalotools/analysis.py
ahfhalotools/filetools.py
ahfhalotools/objects.py
ahfhalotools/plotting/__init__.py
ahfhalotools/plotting/plot3D.py
ahfhalotools/plotting/snapsplot.py
ahfhalotools-1.1.1.dist-info/LICENSE
ahfhalotools-1.1.1.dist-info/METADATA
ahfhalotools-1.1.1.dist-info/WHEEL
ahfhalotools-1.1.1.dist-info/top_level.txt
ahfhalotools-1.1.1.dist-info/RECORD
