Metadata-Version: 2.1
Name: ahfhalotools
Version: 1.1.1
Summary: A Python 3 library for the analysis of data produced by AMIGA's Halo Finder (AHF).
Home-page: https://github.com/BenDavisonPetch/ahfhalotools
Author: Ben Davison-Petch
Author-email: bendpetch@gmail.com
License: UNKNOWN
Platform: UNKNOWN
Classifier: Programming Language :: Python :: 3
Classifier: License :: OSI Approved :: MIT License
Classifier: Operating System :: OS Independent
Requires-Python: >=3.6
License-File: LICENSE
